{"name": "Katherine", "generation": 0, "children": {"2": {"name": "Richard", "generation": 1, "children": {"4": {"name": "Rebecca", "generation": 2, "children": {"12": {"name": "Billy", "generation": 3, "children": {"14": {"name": "Jimmy", "generation": 4, "children": {"27": {"name": "Ralph", "generation": 5, "children": {}}, "20": {"name": "Doris", "generation": 5, "children": {}}, "23": {"name": "Fred", "generation": 5, "children": {}}, "16": {"name": "Gloria", "generation": 5, "children": {"19": {"name": "Adam", "generation": 6, "children": {}}}}}}, "29": {"name": "Joshua", "generation": 4, "children": {}}}}, "6": {"name": "Melissa", "generation": 3, "children": {"8": {"name": "Pamela", "generation": 4, "children": {"10": {"name": "Jerry", "generation": 5, "children": {}}}}}}}}, "43": {"name": "Herbert", "generation": 2, "children": {}}, "31": {"name": "Michelle", "generation": 2, "children": {"33": {"name": "Janet", "generation": 3, "children": {"40": {"name": "Anne", "generation": 4, "children": {}}, "37": {"name": "Denise", "generation": 4, "children": {"39": {"name": "Mario", "generation": 5, "children": {}}}}, "35": {"name": "Walter", "generation": 4, "children": {}}}}}}, "44": {"name": "Esther", "generation": 2, "children": {"48": {"name": "Gerald", "generation": 3, "children": {}}, "46": {"name": "Rachel", "generation": 3, "children": {}}}}}}}}